LICENSE
MANIFEST.in
README.rst
setup.py
bin/copy
bin/paste
copypaste/__init__.py
copypaste/cli.py
copypaste/unix.py
copypaste/win.py
copypaste.egg-info/PKG-INFO
copypaste.egg-info/SOURCES.txt
copypaste.egg-info/dependency_links.txt
copypaste.egg-info/not-zip-safe
copypaste.egg-info/requires.txt
copypaste.egg-info/top_level.txt