Metadata-Version: 1.1
Name: copypaste
Version: 0.2
Summary: Platform independent copy + paste library for Python
Home-page: http://gr1n.github.io/copypaste/
Author: Nikita Grishko
Author-email: grin.minsk@gmail.com
License: MIT
Platform: UNKNOWN
Classifier: License :: OSI Approved :: MIT License
Classifier: Programming Language :: Python
Classifier: Programming Language :: Python :: 2
Classifier: Programming Language :: Python :: 2.6
Classifier: Programming Language :: Python :: 2.7
Classifier: Programming Language :: Python :: 3
Classifier: Programming Language :: Python :: 3.3
Classifier: Programming Language :: Python :: Implementation :: CPython
Classifier: Programming Language :: Python :: Implementation :: IronPython
